{
	"partitions" : [
		{
			"name" : "Top",
			"pins" : [
				{
					"name" : "six_led[0]",
					"strict" : false
				},
				{
					"name" : "six_led[1]",
					"strict" : false
				},
				{
					"name" : "six_led[2]",
					"strict" : false
				},
				{
					"name" : "six_led[3]",
					"strict" : false
				},
				{
					"name" : "six_led[4]",
					"strict" : false
				},
				{
					"name" : "six_led[5]",
					"strict" : false
				},
				{
					"name" : "six_led[6]",
					"strict" : false
				},
				{
					"name" : "six_led[7]",
					"strict" : false
				},
				{
					"name" : "six_led[8]",
					"strict" : false
				},
				{
					"name" : "six_led[9]",
					"strict" : false
				},
				{
					"name" : "six_led[10]",
					"strict" : false
				},
				{
					"name" : "six_led[11]",
					"strict" : false
				},
				{
					"name" : "six_led[12]",
					"strict" : false
				},
				{
					"name" : "six_led[13]",
					"strict" : false
				},
				{
					"name" : "six_led[14]",
					"strict" : false
				},
				{
					"name" : "six_led[15]",
					"strict" : false
				},
				{
					"name" : "six_led[16]",
					"strict" : false
				},
				{
					"name" : "six_led[17]",
					"strict" : false
				},
				{
					"name" : "six_led[18]",
					"strict" : false
				},
				{
					"name" : "six_led[19]",
					"strict" : false
				},
				{
					"name" : "six_led[20]",
					"strict" : false
				},
				{
					"name" : "six_led[21]",
					"strict" : false
				},
				{
					"name" : "six_led[22]",
					"strict" : false
				},
				{
					"name" : "six_led[23]",
					"strict" : false
				},
				{
					"name" : "six_led[24]",
					"strict" : false
				},
				{
					"name" : "six_led[25]",
					"strict" : false
				},
				{
					"name" : "six_led[26]",
					"strict" : false
				},
				{
					"name" : "six_led[27]",
					"strict" : false
				},
				{
					"name" : "six_led[28]",
					"strict" : false
				},
				{
					"name" : "six_led[29]",
					"strict" : false
				},
				{
					"name" : "six_led[30]",
					"strict" : false
				},
				{
					"name" : "six_led[31]",
					"strict" : false
				},
				{
					"name" : "six_led[32]",
					"strict" : false
				},
				{
					"name" : "six_led[33]",
					"strict" : false
				},
				{
					"name" : "six_led[34]",
					"strict" : false
				},
				{
					"name" : "six_led[35]",
					"strict" : false
				},
				{
					"name" : "six_led[36]",
					"strict" : false
				},
				{
					"name" : "six_led[37]",
					"strict" : false
				},
				{
					"name" : "six_led[38]",
					"strict" : false
				},
				{
					"name" : "six_led[39]",
					"strict" : false
				},
				{
					"name" : "six_led[40]",
					"strict" : false
				},
				{
					"name" : "six_led[41]",
					"strict" : false
				},
				{
					"name" : "rst_n",
					"strict" : false
				},
				{
					"name" : "clk_50MHz",
					"strict" : false
				}
			]
		}
	]
}